schools/__init__.py
schools/_base_client.py
schools/_client.py
schools/_compat.py
schools/_constants.py
schools/_exceptions.py
schools/_files.py
schools/_models.py
schools/_qs.py
schools/_resource.py
schools/_response.py
schools/_streaming.py
schools/_types.py
schools/_version.py
schools/py.typed
schools/_utils/__init__.py
schools/_utils/_compat.py
schools/_utils/_datetime_parse.py
schools/_utils/_logs.py
schools/_utils/_proxy.py
schools/_utils/_reflection.py
schools/_utils/_resources_proxy.py
schools/_utils/_streams.py
schools/_utils/_sync.py
schools/_utils/_transform.py
schools/_utils/_typing.py
schools/_utils/_utils.py
schools/lib/.keep
schools/resources/__init__.py
schools/resources/health.py
schools/resources/root.py
schools/resources/schools.py
schools/resources/sync.py
schools/types/__init__.py
schools/types/health_check_response.py
schools/types/root_retrieve_response.py
schools/types/school_by_authority_params.py
schools/types/school_by_city_params.py
schools/types/school_by_status_params.py
schools/types/school_by_suburb_params.py
schools/types/school_list_params.py
schools/types/school_list_response.py
schools/types/school_retrieve_response.py
schools/types/school_search_params.py
schools/types/school_search_response.py
schools/types/sync_get_status_response.py
schools/types/sync_trigger_response.py
schools_sdk-0.2.1.dist-info/METADATA
schools_sdk-0.2.1.dist-info/WHEEL
schools_sdk-0.2.1.dist-info/licenses/LICENSE
schools_sdk-0.2.1.dist-info/RECORD
